uipath_cloud/__init__.py
uipath_cloud-0.0.1.dist-info/LICENSE
uipath_cloud-0.0.1.dist-info/METADATA
uipath_cloud-0.0.1.dist-info/WHEEL
uipath_cloud-0.0.1.dist-info/top_level.txt
uipath_cloud-0.0.1.dist-info/RECORD
